osd_text_extractor/__init__.py
osd_text_extractor/py.typed
osd_text_extractor/application/exceptions/__init__.py
osd_text_extractor/application/exceptions/exceptions.py
osd_text_extractor/application/use_cases/__init__.py
osd_text_extractor/application/use_cases/extract_text_use_case.py
osd_text_extractor/domain/entities/__init__.py
osd_text_extractor/domain/entities/plain_text.py
osd_text_extractor/domain/exceptions/__init__.py
osd_text_extractor/domain/exceptions/exceptions.py
osd_text_extractor/domain/interfaces/__init__.py
osd_text_extractor/domain/interfaces/text_extractor.py
osd_text_extractor/infrastructure/di/__init__.py
osd_text_extractor/infrastructure/di/container.py
osd_text_extractor/infrastructure/di/providers.py
osd_text_extractor/infrastructure/exceptions/__init__.py
osd_text_extractor/infrastructure/exceptions/exceptions.py
osd_text_extractor/infrastructure/extractors/__init__.py
osd_text_extractor/infrastructure/extractors/_csv.py
osd_text_extractor/infrastructure/extractors/_docx.py
osd_text_extractor/infrastructure/extractors/_epub.py
osd_text_extractor/infrastructure/extractors/_fb2.py
osd_text_extractor/infrastructure/extractors/_html.py
osd_text_extractor/infrastructure/extractors/_json.py
osd_text_extractor/infrastructure/extractors/_md.py
osd_text_extractor/infrastructure/extractors/_ods.py
osd_text_extractor/infrastructure/extractors/_odt.py
osd_text_extractor/infrastructure/extractors/_pdf.py
osd_text_extractor/infrastructure/extractors/_rtf.py
osd_text_extractor/infrastructure/extractors/_txt.py
osd_text_extractor/infrastructure/extractors/_xlsx.py
osd_text_extractor/infrastructure/extractors/_xml.py
osd_text_extractor/infrastructure/extractors/extractor_factory.py
osd_text_extractor/infrastructure/extractors/utils/__init__.py
osd_text_extractor/infrastructure/extractors/utils/decode_to_utf8.py
osd_text_extractor/infrastructure/extractors/utils/xml_node_to_plain_text.py
osd_text_extractor/presentation/__init__.py
osd_text_extractor-0.1.1.dist-info/licenses/LICENSE
osd_text_extractor-0.1.1.dist-info/METADATA
osd_text_extractor-0.1.1.dist-info/WHEEL
osd_text_extractor-0.1.1.dist-info/top_level.txt
osd_text_extractor-0.1.1.dist-info/RECORD
