Metadata-Version: 2.4
Name: osd-text-extractor
Version: 0.1.1
Summary: A Python library for extracting plain text from various document formats for LLM and NLP purposes
Author-email: OneSlap Team <lxarbuz@gmail.com>
License: MIT License
Project-URL: Homepage, https://github.com/oneslapdeal/osd_text_extractor
Project-URL: Bug Reports, https://github.com/oneslapdeal/osd_text_extractor/issues
Project-URL: Source, https://github.com/oneslapdeal/osd_text_extractor
Project-URL: Documentation, https://github.com/oneslapdeal/osd_text_extractor#readme
Keywords: text-extraction,pdf,docx,xlsx,html,llm,nlp
Classifier: Development Status :: 4 - Beta
Classifier: Intended Audience :: Developers
Classifier: License :: OSI Approved :: MIT License
Classifier: Operating System :: OS Independent
Classifier: Programming Language :: Python :: 3
Classifier: Programming Language :: Python :: 3.12
Classifier: Programming Language :: Python :: 3.13
Classifier: Topic :: Text Processing
Classifier: Topic :: Software Development :: Libraries :: Python Modules
Classifier: Topic :: Office/Business :: Office Suites
Classifier: Typing :: Typed
Requires-Python: >=3.12
License-File: LICENSE
Requires-Dist: beautifulsoup4>=4.13.5
Requires-Dist: defusedxml>=0.7.1
Requires-Dist: dishka>=1.6.0
Requires-Dist: emoji>=2.14.1
Requires-Dist: lxml>=6.0.1
Requires-Dist: odfpy>=1.4.1
Requires-Dist: openpyxl>=3.1.5
Requires-Dist: pymupdf>=1.26.4
Requires-Dist: python-docx>=1.2.0
Requires-Dist: striprtf>=0.0.29
Provides-Extra: dev
Requires-Dist: setuptools>=80.9.0; extra == "dev"
Requires-Dist: wheel>=0.45.1; extra == "dev"
Requires-Dist: build>=1.2.0; extra == "dev"
Requires-Dist: twine>=6.0.0; extra == "dev"
Requires-Dist: bandit>=1.8.6; extra == "dev"
Requires-Dist: mypy>=1.17.1; extra == "dev"
Requires-Dist: pylint>=3.3.8; extra == "dev"
Requires-Dist: ruff>=0.6.9; extra == "dev"
Requires-Dist: pytest>=8.4.1; extra == "dev"
Requires-Dist: pytest-asyncio>=1.1.0; extra == "dev"
Requires-Dist: pytest-cov>=6.2.1; extra == "dev"
Requires-Dist: safety>=3.2.8; extra == "dev"
Requires-Dist: pre-commit>=3.8.0; extra == "dev"
Dynamic: license-file
